COPYING
MANIFEST.in
setup.py
tox.ini
single_project/__init__.py
single_project/manage.py
single_project/settings.py
single_project/urls.py
single_project/wsgi.py
src/django_pgpmailman/__init__.py
src/django_pgpmailman/apps.py
src/django_pgpmailman/decorators.py
src/django_pgpmailman/forms.py
src/django_pgpmailman/models.py
src/django_pgpmailman/plugin.py
src/django_pgpmailman/urls.py
src/django_pgpmailman.egg-info/PKG-INFO
src/django_pgpmailman.egg-info/SOURCES.txt
src/django_pgpmailman.egg-info/dependency_links.txt
src/django_pgpmailman.egg-info/requires.txt
src/django_pgpmailman.egg-info/top_level.txt
src/django_pgpmailman/static/django-pgpmailman/libs/bootstrap/css/bootstrap-old.min.css
src/django_pgpmailman/static/django-pgpmailman/libs/bootstrap/css/bootstrap.min.css
src/django_pgpmailman/static/django-pgpmailman/libs/bootstrap/js/bootstrap-old.min.js
src/django_pgpmailman/static/django-pgpmailman/libs/bootstrap/js/bootstrap.min.js
src/django_pgpmailman/static/django-pgpmailman/libs/jquery/js/jquery-old.min.js
src/django_pgpmailman/static/django-pgpmailman/libs/jquery/js/jquery.min.js
src/django_pgpmailman/templates/account/base.html
src/django_pgpmailman/templates/django_mailman3/base.html
src/django_pgpmailman/templates/django_pgpmailman/base.html
src/django_pgpmailman/templates/django_pgpmailman/index.html
src/django_pgpmailman/templates/django_pgpmailman/chunks/menu-large.html
src/django_pgpmailman/templates/django_pgpmailman/chunks/menu.html
src/django_pgpmailman/templates/django_pgpmailman/chunks/navbar.html
src/django_pgpmailman/templates/django_pgpmailman/list/create.html
src/django_pgpmailman/templates/django_pgpmailman/list/encryption_settings.html
src/django_pgpmailman/templates/django_pgpmailman/list/key_management.html
src/django_pgpmailman/templates/django_pgpmailman/list/misc_settings.html
src/django_pgpmailman/templates/django_pgpmailman/list/nav.html
src/django_pgpmailman/templates/django_pgpmailman/list/signature_settings.html
src/django_pgpmailman/templates/django_pgpmailman/list/summary.html
src/django_pgpmailman/templates/django_pgpmailman/user/summary.html
src/django_pgpmailman/views/__init__.py
src/django_pgpmailman/views/list.py
